kareem/__init__.py
kareem/a1.py
kareem/a2.py
libKareem-0.0.1.dist-info/LICENSE.txt
libKareem-0.0.1.dist-info/METADATA
libKareem-0.0.1.dist-info/WHEEL
libKareem-0.0.1.dist-info/top_level.txt
libKareem-0.0.1.dist-info/RECORD
