Metadata-Version: 2.1
Name: libKareem
Version: 0.0.1
Summary: libKareem
Home-page: UNKNOWN
Author: Kareem
Author-email: mokareem39@gmail.com
License: UNKNOWN
Keywords: arithmetic,math,mathematics,python tutorial,Mo kareem
Platform: UNKNOWN
Classifier: Development Status :: 1 - Planning
Classifier: Intended Audience :: Developers
Classifier: Programming Language :: Python :: 3
Classifier: Operating System :: Unix
Classifier: Operating System :: MacOS :: MacOS X
Classifier: Operating System :: Microsoft :: Windows
